replace_missing_values/__init__.py
replace_missing_values/replace_missing_values_101883055.py
Replace_Missing_Values_101883055-0.0.2.dist-info/LICENSE
Replace_Missing_Values_101883055-0.0.2.dist-info/METADATA
Replace_Missing_Values_101883055-0.0.2.dist-info/WHEEL
Replace_Missing_Values_101883055-0.0.2.dist-info/top_level.txt
Replace_Missing_Values_101883055-0.0.2.dist-info/RECORD
