Metadata-Version: 2.1
Name: Replace-Missing-Values-101883055
Version: 0.0.2
Summary: Replacing NaN values in the dataset using Simple Imputer method.
Home-page: https://github.com/pypa/sampleproject
Author: Naman Goyal
Author-email: ngoyal_be17@thapar.edu
License: UNKNOWN
Platform: UNKNOWN
Classifier: Programming Language :: Python :: 3
Classifier: License :: OSI Approved :: MIT License
Classifier: Operating System :: OS Independent
Requires-Python: >=3
